roby/Alterations.py
roby/CloudTools.py
roby/EnvironmentRTest.py
roby/RobustnessNN.py
roby/RobustnessResults.py
roby/Utility.py
roby/__init__.py
roby-0.0.4.dist-info/METADATA
roby-0.0.4.dist-info/WHEEL
roby-0.0.4.dist-info/top_level.txt
roby-0.0.4.dist-info/RECORD
