Metadata-Version: 2.1
Name: roby
Version: 0.0.4
Summary: A general framework to analyse the robustness of a Neural Network
Home-page: UNKNOWN
Author: University of Bergamo
Author-email: andrea.bombarda@unibg.it
License: UNKNOWN
Platform: UNKNOWN
Requires-Python: >=3.6, <=3.9.11
Requires-Dist: numpy (==1.26.4)
Requires-Dist: opencv-python (>=4.0)
Requires-Dist: Pillow (>=5.4.1)
Requires-Dist: Keras (>=2.2.4)
Requires-Dist: tensorflow (==2.15.1)
Requires-Dist: scikit-learn
Requires-Dist: PyDrive (>=1.3.1)
Requires-Dist: scipy (>=1.4.1)
Requires-Dist: oauth2client (>=4.1.3)
Requires-Dist: matplotlib (>=3.0.2)
Requires-Dist: protobuf (==3.20.3)
Requires-Dist: typing (>=3.7.4)
Requires-Dist: imutils (>=0.5.2)
Requires-Dist: sympy
